more.transaction-0.8-py3.5-nspkg.pth
more/transaction/__init__.py
more/transaction/compat.py
more/transaction/main.py
more/transaction/tests/test_default_commit_veto.py
more/transaction/tests/test_transaction.py
more.transaction-0.8.dist-info/DESCRIPTION.rst
more.transaction-0.8.dist-info/METADATA
more.transaction-0.8.dist-info/metadata.json
more.transaction-0.8.dist-info/namespace_packages.txt
more.transaction-0.8.dist-info/RECORD
more.transaction-0.8.dist-info/top_level.txt
more.transaction-0.8.dist-info/WHEEL
