Metadata-Version: 2.0
Name: more.transaction
Version: 0.8
Summary: transaction integration for Morepath
Home-page: https://github.com/morepath/more.transaction
Author: Martijn Faassen
Author-email: faassen@startifact.com
License: BSD
Keywords: morepath sqlalchemy zodb transaction
Platform: UNKNOWN
Classifier: Intended Audience :: Developers
Classifier: License :: OSI Approved :: BSD License
Classifier: Environment :: Web Environment
Classifier: Topic :: Software Development :: Libraries :: Application Frameworks
Classifier: Topic :: Internet :: WWW/HTTP :: WSGI
Classifier: Programming Language :: Python :: 2.7
Classifier: Programming Language :: Python :: 3.3
Classifier: Programming Language :: Python :: 3.4
Classifier: Programming Language :: Python :: 3.5
Classifier: Programming Language :: Python :: Implementation :: PyPy
Classifier: Development Status :: 5 - Production/Stable
Requires-Dist: setuptools
Requires-Dist: morepath (>=0.15)
Requires-Dist: transaction
Provides-Extra: test
Requires-Dist: coverage; extra == 'test'
Requires-Dist: pytest (>=2.6.0); extra == 'test'
Requires-Dist: pytest-cov; extra == 'test'
Requires-Dist: webtest; extra == 'test'
